gitlab_registry_cleanup/__init__.py
gitlab_registry_cleanup/_version.py
gitlab_registry_cleanup/cleanup.py
gitlab_registry_cleanup/cli.py
gitlab_registry_cleanup/registry.py
gitlab_registry_cleanup-0.1.7.dist-info/METADATA
gitlab_registry_cleanup-0.1.7.dist-info/RECORD
gitlab_registry_cleanup-0.1.7.dist-info/WHEEL
gitlab_registry_cleanup-0.1.7.dist-info/entry_points.txt
gitlab_registry_cleanup-0.1.7.dist-info/top_level.txt
