Metadata-Version: 2.1
Name: gitlab-registry-cleanup
Version: 0.1.7
Summary: A tool to clean up untagged GitLab registry images.
Home-page: https://github.com/sciapp/gitlab-registry-cleanup
Author: Ingo Heimbach
Author-email: i.heimbach@fz-juelich.de
License: MIT
Keywords: Git,GitLab,Docker,Registry,Cleanup
Platform: UNKNOWN
Classifier: Development Status :: 5 - Production/Stable
Classifier: Environment :: Console
Classifier: Intended Audience :: System Administrators
Classifier: License :: OSI Approved :: MIT License
Classifier: Programming Language :: Python :: 3
Classifier: Programming Language :: Python :: 3.3
Classifier: Programming Language :: Python :: 3.4
Classifier: Programming Language :: Python :: 3.5
Classifier: Programming Language :: Python :: 3.6
Classifier: Programming Language :: Python :: 3 :: Only
Classifier: Topic :: System :: Systems Administration
Requires-Python: ~=3.3
Requires-Dist: gitlab-registry-usage (>=0.2.1)
Requires-Dist: typing
